simple_api_framework/__init__.py
simple_api_framework/redis.py
simple_api_framework/db/__init__.py
simple_api_framework/db/mongo.py
simple_api_framework/monitors/__init__.py
simple_api_framework-0.0.60.dist-info/METADATA
simple_api_framework-0.0.60.dist-info/WHEEL
simple_api_framework-0.0.60.dist-info/top_level.txt
simple_api_framework-0.0.60.dist-info/RECORD
