Metadata-Version: 2.1
Name: simple-api-framework
Version: 0.0.60
Summary: Simple async API framework
Author: Ihor Maiorov
Author-email: ihor.maioroff@gmail.com
License: MIT
Keywords: tornado,api,simple-api
Classifier: Development Status :: 3 - Alpha
Classifier: Intended Audience :: Developers
Classifier: License :: OSI Approved :: MIT License
Classifier: Programming Language :: Python :: 3
Requires-Dist: tornado (>=6.2)
Requires-Dist: python-dotenv (>=0.21.0)
Requires-Dist: python-magic (>=0.4.27)
Requires-Dist: redis (>=4.3.5)
Requires-Dist: aiopg (>=1.3.5)
Requires-Dist: psycopg2-binary (>=2.9.5)
Requires-Dist: datadog (>=0.44.0)
Requires-Dist: sentry-sdk (>=1.9.4)
Requires-Dist: ddtrace (>=1.6.3)
Requires-Dist: motor (>=3.1.1)
